MailboxValidator/SingleValidation.py
MailboxValidator/__init__.py
MailboxValidator/email_validation.py
MailboxValidator-1.3.1.dist-info/LICENSE.txt
MailboxValidator-1.3.1.dist-info/METADATA
MailboxValidator-1.3.1.dist-info/WHEEL
MailboxValidator-1.3.1.dist-info/top_level.txt
MailboxValidator-1.3.1.dist-info/RECORD
